tacrpy/__init__.py
tacrpy/data_operations.py
tacrpy/analytics/__init__.py
tacrpy/data_fetcher/__init__.py
tacrpy/data_fetcher/googlesheets.py
tacrpy/data_fetcher/isvavai.py
tacrpy/data_fetcher/ssot.py
tacrpy/datahub/__init__.py
tacrpy/datahub/data_lineage.py
tacrpy/datahub/datasets.py
tacrpy/datahub/glossary.py
tacrpy/datahub/import_checks.py
tacrpy/datahub/openapi.py
sista_tacrpy-1.0.10.dist-info/METADATA
sista_tacrpy-1.0.10.dist-info/WHEEL
sista_tacrpy-1.0.10.dist-info/top_level.txt
sista_tacrpy-1.0.10.dist-info/RECORD
