Metadata-Version: 2.4
Name: SISTA-tacrpy
Version: 1.0.10
Summary: stahovani dat ze sista
Author: velci panove tacru
Author-email: rozalie.bilkova@tacr.cz
Project-URL: Documentation, https://youtu.be/1RulQYSl1aw?feature=shared
Requires-Dist: pandas
Requires-Dist: gspread
Requires-Dist: numpy
Requires-Dist: requests
Requires-Dist: unidecode
Dynamic: author
Dynamic: author-email
Dynamic: description
Dynamic: project-url
Dynamic: requires-dist
Dynamic: summary
